src/exemple_package_aliciane-pinault/__init__.py
src/exemple_package_aliciane-pinault/main.py
example_package_aliciane_pinault-3.8.14.dist-info/METADATA
example_package_aliciane_pinault-3.8.14.dist-info/WHEEL
example_package_aliciane_pinault-3.8.14.dist-info/licenses/LICENSE
example_package_aliciane_pinault-3.8.14.dist-info/RECORD
